PyFolioC/PyFolioC.py
PyFolioC/__init__.py
PyFolioC-0.1.dist-info/METADATA
PyFolioC-0.1.dist-info/WHEEL
PyFolioC-0.1.dist-info/top_level.txt
PyFolioC-0.1.dist-info/RECORD
