Metadata-Version: 2.1
Name: PyFolioC
Version: 0.1
Summary: Portfolio Optimization Package
Home-page: https://github.com/NailKhelifa/PyFolioC
Author: Naïl Khelifa
Author-email: nail.khelifa@ensae.fr
License: UNKNOWN
Platform: UNKNOWN
Classifier: Programming Language :: Python :: 3
Classifier: License :: OSI Approved :: MIT License
Classifier: Operating System :: OS Independent
Requires-Dist: numpy (>=1.24.3)
Requires-Dist: pandas (>=2.0.3)
Requires-Dist: scipy (>=1.11.1)
Requires-Dist: matplotlib (>=3.7.2)
Requires-Dist: seaborn (>=0.12.2)
Requires-Dist: PyPortfolioOpt (>=1.5.4)
